{
  "intents": [
    {
      "tag": "greeting",
      "patterns": [
        "Hi",
        "Is anyone there?",
        "Hey",
        "Good day",
        "How are you",
        "Hello"

      ],
      "responses": [
         "I'm Kayla Virtual Assistant Of Royal Bank How Can I  Help You?"
      ]
    },
    {
      "tag": "goodbye",
      "patterns": ["Bye", "See you later", "Goodbye"],
      "responses": [
        "See you later, thanks for visiting",
        "Bye! Come back again soon.",
        "Have a nice day"

      ]
    },
    {
      "tag": "thanks",
      "patterns": ["Thanks", "Thank you", "That's helpful", "Thank's a lot!"],
      "responses": ["Happy to help!", "Any time!", "My pleasure"]
    },
    {
      "tag": "loan",
      "patterns": [
        "loans",
        "Do you provide loan?",
        "what type of loan your bank have?",
        "Can i know about loans?",
        "loan types"

      ],
      "responses": [
        "Yes we provides multy loan systems.",
        "We provide\nPersonal loans\nHome loans\nEducational loans\nVehicle loans\nWhich one is more suitable to you?\n"
      ]
    },
    {
      "tag": "account",
      "patterns": [
        "How many types of accounts your bank have?",
        "What are those two type of accounts?",
        "How Can I open an account?",
        "How to open an account?",
         "Online account"
      ],
      "responses": [
        "We have personal and business accounts. Which account type do you prefer?"
      ]
    },
       {
      "tag": "educational",
      "patterns": [
        "Do you have educational loans?",
        "Educational loans",
        "How Can I Get The Educational Loan?"
      ],
      "responses": [
        "You are interseted in Educational loans.\nFor more information, please go to https://rbcbank.com/loans/educational loan\n"
      ]
    },
    {
      "tag": "personal",
      "patterns": [
        "bank has personal type account?",
        "how to open personal account in bank?",
        "Can i know about personal type accounts?",
        "Tell  about personal type account?",
        "Personal type account examples?"
      ],
      "responses": [
        "We have following Accounts:\nSavings,\nCurrent,\nFixed,\nSenior Citizen,\nWhich one is more suitable to you?"
      ]
    },
     {
      "tag": "saving",
      "patterns": [
       "saving account",
        "saving",
        "How to open savings account?"
      ],
      "responses": [
        "You are interseted in opening a savings account. \nPlease go to https://rbcbank.com/savings/info\n"
      ]
    },
    {
      "tag": "business",
      "patterns": [
        "Do your bank has buisness account?",
        "How Can i open buisness account in your bank",
        "What i need to open buisness type accounts?",
        "Tell me about personal type accounts."
      ],
      "responses": [
        "Yes we have buisness account",
        "General current Account\nSupreme Current Account\nPaymet Guaranteed Cheque Account\nWhich one is more suitable to you?\n"
      ]
    },
    {
      "tag": "contact",
      "patterns": [
        "contact customer care?",
        "customer care details?",
        "contact details?",
        "contact bank customer care details?",
        "contact customer care number?",
        "contact no?"
      ],
      "responses": [
        "Email id :- royal_bank@info.com , Head Office :- 112/3 St.Clair Road, Wellawatta. Contact No :- 011-637 2982/011-879 617,",
        "Contact No :- 011-637 2982/011-879 617"
      ]
    },
     {
      "tag": "branch",
      "patterns": [
        "how many branches your bank have?",
        "how many branches your bank has?",
        "Where is your branches located?",
        "Where is your branch locations",
        "Branch locations",
        "branch located areas?"
      ],
      "responses": [
        "We have 10 Branches.",
        "Our Head Branch is Located in Wellawatta and other branches are listed as follows Moratuwa,  Kalutara, Kandy, Dambulla, \n Trincomalee,  Jaffna, Buttala, Matara and Galle"
      ]
    },
    {
      "tag": "E-Banking ",
      "patterns": [
        "Do your Bank Has E-Banking?",
        "Can i know about E-Banking?",
        "Can you explain about E-Banking?",
        "E-Bank details?"
      ],
      "responses": [
        "Yes We have E-Banking System.",
        "It's a system you can do your all banking work via online."
      ]
    },
       {
      "tag": "interest",
      "patterns": [
        "interest",
        "interest rates",
        "Can i know the interest rate your bank provide?",
        "Can i know about interest ratio in your bank?"
      ],
      "responses": [
        "we give 2.5 % intrest in our bank."
      ]
    },
    {
      "tag": "debit card",
      "patterns": [
        "Can i know about debit card?",
        "Can you tell about debit card you provide?"
      ],
      "responses": [
        "The Royal Bank Visa and Mastercard Debit Cards are the easiest \n and most convenient way to purchase \n goods and services from any outlet. for further details contact our hot line..."
      ]
    },
     {
      "tag": "credit card",
      "patterns": [
        "Can i know about credit card?",
        "Can you tell about credit card you provide?"
      ],
      "responses": [
        "Convenience, speed and security. These features have been the  \n benchmarks of Royal Bank Credit cards.for further details contact our hot line..."
      ]
    },
     {
      "tag": "thanks",
      "patterns": [
        "Thank You",
         "Thanks",
        "Great",
        "Tks",
        "Thanks a lot"
      ],
      "responses": [
        "Happy to help, Anytime!"
      ]
    },
     {
      "tag": "game",
      "patterns": [
        "what is game?",
        "tell about game"
      ],
      "responses": [
        "aanbbh  sba kabad"
      ]
    }
  ]
}
